Workbook

Sheet Conciliacion_Transferencias
A1: Fecha | B1: Folio | C1: Cliente | D1: Servicio (s) | E1: Banco | F1: Monto | G1: ✅ Conciliado | H1: 💳 Concepto Banco | I1: 🔍 Observaciones
A2: 45977.042 | B2: 0-18592 | C2: Adan Mora | D2: Aveo | F2: 900 | G2: TRUE | H2: SPEI RECIBIDOMercado Pago/0139657603 722 4655821MERCADO*PAGO | I2: En esta falto $1
A3: 45977.042 | B3: 0-18743 | C3: Jorge | D3: sala + 4 sillas | F3: 1200 | G3: TRUE | H3: SPEI RECIBIDOBANAMEX/0139909434 002 0161125Lavado Jorge Herrera
A4: 45977.042 | B4: 0-18440 | C4: Georgina Crespo | D4: Sala L 5 plazas + 8 sillas + cabecera + box | F4: 1750 | G4: TRUE | H4: SPEI RECIBIDOSANTANDER/0140050765 014 9755000TRANSFERENCIA A LAVASMART SA D
A5: 45977.042 | B5: 0-18241 | C5: Laura Romero | D5: sala 3 y 2 px+ sofa cama+ colchon+ 6 sillas | E5: BANCOMER | F5: 2200 | G5: TRUE | H5: PAGO CUENTA DE TERCERO/ 0017746057 BNET 1584201510 laura Romero
A6: 45977.042 | B6: 0-18157 | C6: Sandra Diego | D6: colchón matrimonial | E6: SANTANDER | F6: 1200 | G6: TRUE | H6: SPEI RECIBIDOSANTANDER/0139758170 014 1543571TRANSFERENCIA A SANDRA DIEGO F
A7: 45978.042 | B7: 0-18163 | C7: Javier Hernandez | D7: Sala Grande + 4 sillas | E7: BANCOMER | F7: 1200 | G7: TRUE | H7: PAGO CUENTA DE TERCERO/ 0050780773 BNET 2912115158 javier hernandez
A8: 45978.042 | B8: 0-18375 | C8: Karen | D8: Sala 3 piezas + colchón + cabecera | E8: BANCOMER | F8: 1800 | G8: TRUE | H8: PAGO CUENTA DE TERCERO/ 0023488351 BNET 1582232138 serv 17 noviembre
A9: 45978.042 | B9: 0-18443 | C9: Abril | D9: 8 Sala para 5 personas + 4 sillas de comedor | E9: SPIN-AZUL | F9: 1000 | G9: TRUE | H9: SPEI RECIBIDOSPIN BY OXXO/0144784269 728 1414656lava
A10: 45978.042 | B10: 0-18595 | C10: Dany Soria | D10: carro chico | E10: BANAMEX | F10: 900 | G10: TRUE | H10: SPEI RECIBIDOBANAMEX/0144712916 002 0171125servicio auto | I10: Faltaba $1 pero si se transfirio
A11: 45978.042 | B11: 0-18746 | C11: Roberto Monzon | D11: Sala 2 piezas + 8 sillas de comedor + Colchón + Cabecera | E11: BANCOMER | F11: 2200 | G11: TRUE | H11: PAGO CUENTA DE TERCERO/ 0043033594 BNET 1217083084 limpieza casa 7 be
A12: 45978.042 | B12: 0-18747 | C12: Elizabeth Godínez | D12: Sala en L para 4 personas + 4 sillas de comedor | E12: SPEI | F12: 1200 | G12: TRUE | H12: SPEI RECIBIDOHSBC/0146144398 021 0171125Transferencia SPEI
A13: 45978.042 | B13: 0-18371 | C13: Karen díazDíaz | D13: Colchón king | E13: BANCOMER | F13: 750 | G13: TRUE | H13: SPEI RECIBIDOBANAMEX/0146461258 002 0171125mario ricci | I13: Hay sobrante de $100 (propina)
A14: 45979.042 | B14: 0-18164 | C14: Iris Gomez | D14: colchón Matrimonial | E14: BANORTE | F14: 750 | G14: TRUE | H14: SPEI RECIBIDOBANORTE/0149392901 072 0251118Clara Iris Gomez Marquez
A15: 45979.042 | B15: 0-18005 | C15: Adriana Gutierrez | D15: Sala L + 4 sillas +banca + colchon | E15: BANCOMER | F15: 1500 | G15: TRUE | H15: PAGO CUENTA DE TERCERO/ 0075425808 BNET 2911252356 Transf a LAVASMART
A16: 45979.042 | B16: 0-18250 | C16: Alejandra ALberchet | D16: sala L + tapete | E16: SPEI | F16: 1500 | G16: TRUE | H16: SPEI RECIBIDOSANTANDER/0152127870 014 8744960TRANSFERENCIA A LAVARSMART SA
A17: 45979.042 | B17: 0-18447 | C17: Myriam Luna | D17: Sala 4 piezas + fiat argo | E17: SPEI | F17: 1800 | G17: TRUE | H17: SPEI RECIBIDOBANAMEX/0150280265 002 0181125MYRIAM LUNA GTZ | I17: En esta falto $1
A18: 45979.042 | B18: 0-18748 | C18: Estela Flores | D18: sala + tapete | E18: BANCOMER | F18: 1350 | G18: TRUE | H18: PAGO CUENTA DE TERCERO/ 0018964785 BNET 1166057640 Servicio E Monjara | I18: En esta falto $1
A19: 45979.042 | B19: 0-18749 | C19: Jorge Gomez | D19: Oso de Peluche | E19: SANTANDER | F19: 600 | G19: TRUE | H19: SPEI RECIBIDOSANTANDER/0150170274 014 0000001TRANSFERENCIA A LAVASMART SA D
A20: 45979.042 | B20: 0-18598 | C20: Omar Martinez | D20: Sala 2 piezas + 8 sillas | E20: BANORTE | F20: 1450 | G20: TRUE | H20: SPEI RECIBIDOBANORTE/0149230521 072 0251118Sin informaci n
A21: 45979.042 | B21: 0-18600 | C21: Vianey oceguera | D21: 2 tapetes 156x225 +120x170 recoleccion | E21: BANCOMER | F21: 1200 | G21: TRUE | H21: PAGO CUENTA DE TERCERO/ 0065959922 BNET 0489023771 lavado alfombra
A22: 45979.042 | B22: 0-18601 | C22: Lourdes García | D22: 2 colchones + 2 sillones individuales | E22: BANAMEX | F22: 1400 | G22: TRUE | H22: SPEI RECIBIDOBANAMEX/0151912234 002 0181125pago lavado
A23: 45980.042 | B23: 0-18007 | C23: Juana | D23: Sala 2 piezas | E23: BANCOMER | F23: 600 | G23: TRUE | H23: PAGO CUENTA DE TERCERO/ 0077535859 BNET 2845125537 Lavado de sala
A24: 45980.042 | B24: 0-18603 | C24: María Nieto | D24: Sala L 3 plazas + sillón individual + 8 sillas (solo asiento) +tapete | E24: BANCOMER | F24: 1800 | G24: TRUE | H24: PAGO CUENTA DE TERCERO/ 0090827189 BNET 1548467788 Maria Nieto juriqu
A25: 45980.042 | B25: 0-18752 | C25: Emma Barrera | D25: Sala en forma de L +8 Cojines | E25: BANCOMER | F25: 1300 | G25: TRUE | H25: PAGO CUENTA DE TERCERO/ 0023450981 BNET 1506954415 Emma Barrera Maque | I25: Esta mal la fecha. Se realizo el servicio el 11/11/2025
A26: 45981.042 | B26: 0-18388 | C26: Marcos | D26: tapete chico | E26: SPEI | F26: 600 | G26: TRUE | H26: SPEI RECIBIDOSTP/0162342274 646 1116837Gto
A27: 45981.042 | B27: 0-18755 | C27: Mario Díaz | D27: Sala en L + 6 sillas + Colchón kin | E27: BANORTE | F27: 1900 | G27: TRUE | H27: SPEI RECIBIDOBANORTE/0161402003 072 0251120lavado colchon
A28: 45982.042 | B28: 0-18758 | C28: Jessica Escamilla | D28: Sala L con cojines | E28: SCOTIABANK | F28: 950 | G28: TRUE | H28: SPEI RECIBIDOSCOTIABANK/0166954586 044 0211125Transferencia a Lavasmart
A29: 45982.042 | B29: 0-18759 | C29: Cesar | D29: 2 sala L + 6 sillas | E29: BANCOMER | F29: 2300 | G29: TRUE | H29: PAGO CUENTA DE TERCERO/ 0034720809 BNET 2713152588 Transf a LAVASMART
A30: 45982.042 | B30: 0-18607 | C30: Ing Gamez | D30: mecedora + 5 sillas | E30: BANORTE | F30: 1400 | G30: TRUE | H30: SPEI RECIBIDOBANORTE/0166858620 072 0251121limpieza de tapetes y sillas
A31: 45982.042 | B31: 0-18609 | C31: Raul Carranza | D31: sala + 6 sillas | E31: SANTANDER | F31: 1250 | G31: TRUE | H31: SPEI RECIBIDOSANTANDER/0167870157 014 2522445TRANSFERENCIA A LAVA SMART
A32: 45982.042 | B32: 0-18610 | C32: José Sanchez | D32: toledo | E32: NU-MORADO | F32: 900 | G32: TRUE | H32: PAGO CUENTA DE TERCERO/ 0062778768 BNET 1542236049 pago servicio
A33: 45982.042 | B33: 0-18013 | C33: Jonathan Martinez | D33: carro chico | F33: 900 | G33: FALSE | H33: PAGO CUENTA DE TERCERO/ 0054216233 BNET 0485580439 Transf a LAVASMART | I33: Borrar
A34: 45982.042 | B34: 0-18014 | C34: Pamela Pintado | D34: Carreola + silla de bebe | F34: 850 | G34: FALSE | I34: Borrar
A35: 45982.042 | B35: 0-18015 | C35: Angel Gonzalez | D35: 3 colchones | F35: 1500 | G35: FALSE | I35: Borrar
A36: 45982.042 | B36: 0-18016 | C36: José Maria Machuca | D36: tapete chico | E36: SANTANDER | F36: 700 | G36: TRUE | H36: SPEI RECIBIDOSANTANDER/0169198782 014 0821954SONIA PEREZ LAVADO DE TAPETE
A37: 45982.042 | B37: 0-18389 | C37: Brenda Vera | D37: Kia Sportage Asientos de Tela | F37: 850 | G37: FALSE | I37: Borrar
A38: 45982.042 | B38: 0-18390 | C38: Eugenia Altamirano | D38: colchón king + mecedora | F38: 1000 | G38: FALSE | I38: Borrar
A39: 45982.042 | B39: 0-18391 | C39: Marycarmen Vazquez | D39: Sala 2 pz + 2 sillones indivuales + 8 sillas + tapete 2x2 | F39: 2500 | G39: FALSE | I39: Borrar
A40: 45982.042 | B40: 0-18261 | C40: Álvaro González | D40: Kia Rio | F40: 850 | G40: FALSE | I40: Borrar
A41: 45982.042 | B41: 0-18263 | C41: Hugo Rangel | D41: fronteir | E41: BANCOMER | F41: 900 | G41: TRUE | H41: PAGO CUENTA DE TERCERO/ 0054216233 BNET 0485580439 Transf a LAVASMART
A42: 45982.042 | B42: 0-18264 | C42: Álvaro González | D42: Kia Rio | E42: INBURSA | F42: 850 | G42: TRUE | H42: SPEI RECIBIDOINBURSA/0168502761 036 2025112Transferencia electronica
A43: 45983.042 | B43: 0-18178 | C43: Margarita Hernandez | D43: sala 3 piezas | E43: SPEI | F43: 850 | G43: TRUE | H43: SPEI RECIBIDOAFIRME/0172952761 062 2105335Margarita hernandez
A44: 45983.042 | B44: 0-18876 | C44: Elizabeth | D44: Carro Chico | E44: SANTANDER | F44: 900 | G44: TRUE | H44: SPEI RECIBIDOSANTANDER/0173956181 014 4066131900 CARLOS LOZADA LAVADO VESTI
A45: 45983.042 | B45: 0-18877 | C45: David Espoinoza | D45: Carro Chico | E45: BANCOMER | F45: 900 | G45: FALSE
A46: 45983.042 | B46: 0-18265 | C46: Jesus Garcia | D46: sala + 6 sillas | E46: BANCOMER | F46: 1250 | G46: TRUE | H46: PAGO CUENTA DE TERCERO/ 0084656561 BNET 1529518416 Jesus Garcia
A47: 45983.042 | B47: 0-18613 | C47: Natanael Millan | D47: patriot | E47: BANORTE | F47: 900 | G47: TRUE | H47: SPEI RECIBIDOBANORTE/0174795260 072 0251122Lavado interiores jeep patriot
A48: 45984.042 | B48: 0-18270 | C48: Tania | D48: 2 tapetes 1.80x2.50 + 8 sillas | E48: BANCOMER | F48: 2400 | G48: TRUE | H48: PAGO CUENTA DE TERCERO/ 0055657706 BNET 2661567144 pago
A49: 45984.042 | B49: 0-18616 | C49: Isabel Espinoza | D49: sala + colchón | E49: BANCOMER | F49: 1200 | G49: TRUE | H49: PAGO CUENTA DE TERCERO/ 0031273263 BNET 1516203623 Isabel Espinoza G
A50: 45985.042 | B50: 0-18188 | C50: Josue Morales | D50: soul | E50: SANTANDER | F50: 900 | G50: FALSE
A51: 45985.042 | B51: 0-18882 | C51: Francisco Tapia | D51: mitsubishi lancer | E51: BANCOMER | F51: 900 | G51: TRUE | H51: PAGO CUENTA DE TERCERO/ 0061277348 BNET 1559180128 lavado mitsubishi | I51: Falto $1
A52: 45985.042 | B52: 0-18883 | C52: Alejandra Rosada | D52: sofá 2 plazas | E52: SANTANDER | F52: 600 | G52: TRUE | H52: SPEI RECIBIDOSANTANDER/0183653284 014 5763311ALEJANDRA ROSADO
A53: 45985.042 | B53: 0-18619 | C53: Carlos Salazar | D53: sala L | E53: BANCOMER | F53: 750 | G53: TRUE | H53: PAGO CUENTA DE TERCERO/ 0069646024 BNET 1519203694 carlos mario salaz
A54: 45985.042 | B54: 0-18881 | C54: Paula Servin | D54: Colchon King + Tapete 2.25x1.55+ Sala de 5 piezas | E54: SCOTIABANK | F54: 2450 | G54: TRUE | H54: SPEI RECIBIDOSCOTIABANK/0182430828 044 0241125Transferencia a Lavasmart
A55: 45982.042 | B55: 0-18870 | C55: Etienne Sticher | D55: tapete recoleccion | E55: NU-MORADO | F55: 850 | G55: TRUE | H55: SPEI RECIBIDONU MEXICO/0169227344 638 0211125Transferencia
A56: 45984.042 | B56: 0-18269 | C56: Jorge Ochoa | D56: Tapete 3x2 | E56: BANCOMER | F56: 1600 | G56: FALSE
A57: 45984.042 | B57: 0-18398 | C57: Nayeli Cervantes | D57: Sala en L | E57: BANCOMER | F57: 1100 | G57: TRUE | H57: PAGO CUENTA DE TERCERO/ 0019751221 BNET 1524413374 Nayeli
A58: 45984.042 | B58: 0-18878 | C58: David Rojas | D58: 2 tapetes (156x223 y 122x178) | E58: HSBC | F58: 1000 | G58: TRUE | H58: SPEI RECIBIDOHSBC/0192735114 021 0261125tapetes Carlos David
A59: 45984.042 | B59: 0-18879 | C59: Lorena Soto | D59: Sala 3 piezas + Tapete+8sillas | E59: BANAMEX | F59: 2000 | G59: TRUE | H59: SPEI RECIBIDOBANAMEX/0187132620 002 0251125Transferencia interbancaria
A60: 45985.042 | B60: 0-18772 | C60: Sandra Puente | D60: soul | E60: BANCOMER | F60: 900 | G60: TRUE | H60: PAGO CUENTA DE TERCERO/ 0053034748 BNET 1546482821 pago Sandra Puente | I60: Falto $1
A61: 45986.042 | B61: 0-18278 | C61: Melanie Roque | D61: sala L + tapete | E61: BANBAJIO | F61: 1200 | G61: TRUE | H61: SPEI RECIBIDOBAJIO/0188001640 030 1010400pago
A62: 45986.042 | B62: 0-18884 | C62: Virginia Castro | D62: 3 Alfombras (5x7 y 2 de 4x5) + 1 Sala en L + 3 Tapetes (2x1, 2.5 x1 y3x2) | E62: BANCOMER | F62: 14860 | G62: TRUE | H62: PAGO CUENTA DE TERCERO/ 0023355033 BNET 0187040865
A63: 45986.042 | B63: 0-18191 | C63: Edna Magallanes | D63: 2 colchones + sofá 2 plazas | E63: BANCOMER | F63: 1600 | G63: TRUE | H63: PAGO CUENTA DE TERCERO/ 0033979393 BNET 1430611077 Edna Magallanes
A64: 45986.042 | B64: 0-18468 | C64: Adriana Valadez | D64: 2 sillones 3 plazas+ 1 sillón 2 plazas + 2 tapetes 170x1 + tapete70x70 | E64: BANCOMER | F64: 3200 | G64: TRUE | H64: PAGO CUENTA DE TERCERO/ 0002045026 BNET 0158467021 adriana valadez
A65: 45986.042 | B65: 0-18776 | C65: Jorge Vázquez | D65: 2 Sillones Individuales + Tapete de 2x2 | E65: BANORTE | F65: 1200 | G65: TRUE | H65: SPEI RECIBIDOBANORTE/0188396955 072 0251125Lavado de alfombra y dos sillo
A66: 45987.042 | B66: 0-18281 | C66: Rosy Pastrana | D66: sala completa | E66: SANTANDER | F66: 1200 | G66: TRUE | H66: SPEI RECIBIDOSANTANDER/0192573431 014 0002611ROSA ENID PASTRANA
A67: 45987.042 | B67: 0-18283 | C67: Carlos Ramírez | D67: Sala para 5 personas | E67: BANCOMER | F67: 850 | G67: TRUE | H67: PAGO CUENTA DE TERCERO/ 0099963589 BNET 1513809304 Carlos Ramirez
A68: 45987.042 | B68: 0-18034 | C68: Melanie Ronzón | D68: 2 tapetes de 1.50x 2.10 RECOLECCIÓN | E68: BANCOMER | F68: 1200 | G68: TRUE | H68: PAGO CUENTA DE TERCERO/ 0040751503 BNET 1562225120 melanie ronzon
A69: 45987.042 | B69: 0-18196 | C69: Rosa Campos | D69: sillon dos plazas | E69: BANAMEX | F69: 750 | G69: FALSE
A70: 45987.042 | B70: 0-18407 | C70: Fernando Alvarez | D70: vestiduras mini cooper | F70: 900 | G70: TRUE | H70: PAGO CUENTA DE TERCERO/ 0039304830 BNET 1526618327 Transf a LAVASMART
A71: 45987.042 | B71: 0-18778 | C71: Diana Pereyra | D71: 4 sillas + banca + 2 sillones Individuales + Sala 3 piezas | E71: HEY BANCO | F71: 2000 | G71: FALSE
A72: 45984.042 | B72: 0-18272 | C72: Diana Mendoza | D72: Tapete 2x2 | E72: BANCOMER | F72: 850 | G72: FALSE
A73: 45987.042 | B73: 0-18307 | C73: Fernando Alvarez | D73: vestiduras mini cooper | E73: BANCOMER | F73: 900 | G73: FALSE
A74: 45988.042 | B74: 0-18199 | C74: Norma Nayeli | D74: sala chica y vestiduras | E74: BANORTE | F74: 1600 | G74: TRUE | H74: SPEI RECIBIDOBANORTE/0199853639 072 0251127norma yaneli quezada diaz
A75: 45988.042 | B75: 0-18037 | C75: Maximiliano García | D75: 2 Sillones individuales | E75: BANCOMER | F75: 700 | G75: TRUE | H75: PAGO CUENTA DE TERCERO/ 0021731456 BNET 1519665563 max garcia
A76: 45988.042 | B76: 0-18038 | C76: Araceli Rodriguez | D76: tapete chico | E76: BANCOMER | F76: 700 | G76: TRUE | H76: PAGO CUENTA DE TERCERO/ 0071676363 BNET 1541648861 lavado tapete
A77: 45988.042 | B77: 0-18039 | C77: Cristina Montero | D77: 4 sillas de comedor | E77: HSBC | F77: 700 | G77: TRUE | H77: SPEI RECIBIDOHSBC/0100272761 021 0271125Cristina moreno lavdo de comed
A78: 45988.042 | B78: 0-18475 | C78: Sra Marques | D78: Tapete + sillón relcinable | E78: BANCOMER | F78: 1100 | G78: TRUE | H78: PAGO CUENTA DE TERCERO/ 0069276062 BNET 2737452993 Fabiola Mendez Cob
A79: 45988.042 | B79: 0-18476 | C79: Antonio Soto | D79: vento | E79: BANCOMER | F79: 900 | G79: TRUE | H79: PAGO CUENTA DE TERCERO/ 0046576176 BNET 1555732916 Transf a LAVASMART | I79: Falto $1
A80: 45988.042 | B80: 0-18477 | C80: Monica Elizondo | D80: colchón ks | E80: BANCOMER | F80: 750 | G80: TRUE | H80: PAGO CUENTA DE TERCERO/ 0061665279 BNET 0185043689 monica elizondo
A81: 45988.042 | B81: 0-18630 | C81: Regina Benhuema | D81: sala 5 plazas | E81: BANCOMER | F81: 750 | G81: TRUE | H81: PAGO CUENTA DE TERCERO/ 0041642276 BNET 1585981360 regina lopez
A82: 45988.042 | B82: 0-18891 | C82: Alejandro Hernández | D82: Auto + tapete 2x1 | E82: BANCOMER | F82: 1550 | G82: TRUE | H82: PAGO CUENTA DE TERCERO/ 0075422982 BNET 0196491138 Alejandro hernande
A83: 45988.042 | B83: 0-18285 | C83: Isaac Hernandez | D83: Nissan March 2020 | E83: BANCOMER | F83: 900 | G83: TRUE | H83: PAGO CUENTA DE TERCERO/ 0056627285 BNET 0118262047 Isaac Hernandez | I83: Falto $1
A84: 45988.042 | B84: 0-18287 | C84: Susana Guerrero | D84: Sala en Herradura | E84: BANCOMER | F84: 1050 | G84: TRUE | H84: PAGO CUENTA DE TERCERO/ 0077210559 BNET 1143617467 lavado sala
A85: 45988.042 | B85: 0-18288 | C85: Raúl Anduaga | D85: Gol 2017 | E85: BANCOMER | F85: 750 | G85: TRUE | H85: PAGO CUENTA DE TERCERO/ 0087530046 BNET 1445889189 Dulce hernandez
A86: 45988.042 | B86: 0-18289 | C86: Angelica Rojo | D86: sala + 4 sillas | E86: BANAMEX | F86: 1200 | G86: TRUE | H86: SPEI RECIBIDOBANAMEX/0100557550 002 0271125Angelica Rojo jasso
A87: 45989.042 | B87: 0-18894 | C87: María Luz | D87: march | E87: BANCOMER | F87: 900 | G87: TRUE | H87: PAGO CUENTA DE TERCERO/ 0077768136 BNET 1553371177 Transf a LAVASMART | I87: Falto $1
A88: 45989.042 | B88: 0-18895 | C88: Maríano | D88: tapete chico | E88: BANCOMER | F88: 650 | G88: TRUE | H88: PAGO CUENTA DE TERCERO/ 0042112935 BNET 2983764486 mariano s a
A89: 45989.042 | B89: 0-18480 | C89: Alejandro Negrete | D89: Sofá 2 plazas + 4 sillas + banco + tapete chico + colchón Queen | E89: Banregio-Verde | F89: 2000 | G89: TRUE | H89: SPEI RECIBIDOBANREGIO/0106679591 058 0281125real
A90: 45989.042 | B90: 0-18481 | C90: Andrés Pozas | D90: 2 colchones (matrimonial y King) + Sala para 5 personas | E90: BANCOMER | F90: 1800 | G90: TRUE | H90: PAGO CUENTA DE TERCERO/ 0076050429 BNET 1507486391 Jazmin Negrete Jua
A91: 45989.042 | B91: 0-18632 | C91: Azucena Rodríguez | D91: Mazda 2 2016 | E91: BANCOMER | F91: 900 | G91: TRUE | H91: PAGO CUENTA DE TERCERO/ 0001890855 BNET 2786688756 Azucena Rodriguez | I91: Falto $1
A92: 45994.042 | B92: 0-18801 | C92: Gaudencia | D92: sala L + love seat | F92: 1450 | G92: TRUE | H92: SPEI RECIBIDOSANTANDER/0105534374 014 6466122TRANSFERENCIA A LAVASMART SA D
A93: 45988.042 | B93: 0-18286 | C93: Blanca | D93: Tapete 2.10 x 3 RECOLECCIÓN | E93: HSBC | F93: 750 | G93: TRUE | H93: SPEI RECIBIDOHSBC/0114488732 021 0291125Blanca Fernandez
A94: 45990.042 | B94: 0-18044 | C94: Carlos Díaz | D94: Nissan X Trail | E94: HSBC | F94: 750 | G94: TRUE | H94: SPEI RECIBIDOHSBC/0114486055 021 0291125Patricia G lavado carro
A95: 45990.042 | B95: 0-18898 | C95: German Sánchez | D95: vento | E95: BANCOMER | F95: 900 | G95: TRUE | H95: PAGO CUENTA DE TERCERO/ 0081373072 BNET 1568448686 German Sanchez | I95: Falto $1
A96: 45990.042 | B96: 0-18294 | C96: Verónica Vigueras | D96: tepete 1.80 x 1.20 | E96: BANAMEX | F96: 600 | G96: TRUE | H96: SPEI RECIBIDOBANAMEX/0114111467 002 0291125lavado de tapete
A97: 45990.042 | B97: 0-17856 | C97: Giovanna | D97: : sala+ 9 cojines+ banca+silla+sofa cama | E97: BANCOMER | F97: 1800 | G97: TRUE | H97: PAGO CUENTA DE TERCERO/ 0019557818 BNET 2897244959 Lavado varios
A98: 45991.042 | B98: 0-18049 | C98: José Presno | D98: 6 sillas | E98: BANAMEX | F98: 750 | G98: TRUE | H98: SPEI RECIBIDOBANAMEX/0120234271 002 0301125Transferencia interbancaria
A99: 45991.042 | B99: 0-18050 | C99: María Ortiz | D99: Colchon Matrimonial | E99: BANCOMER | F99: 800 | G99: TRUE | H99: PAGO CUENTA DE TERCERO/ 0064432203 BNET 1175953308 Maria Ortiz
A100: 45991.042 | B100: 0-17858 | C100: Cristal Gonzalez | D100: Sofa cama con colchón individual + Sala tipo L + cabecera 1.5 x 1.2 | E100: BANAMEX | F100: 2000 | G100: TRUE | H100: SPEI RECIBIDOBANAMEX/0119737749 002 0301125JOSE CARLOS VILLEGAS
...

Sheet Banco
A1: Día | B1: Concepto / Referencia | C1: cargo | D1: Abono | E1: Saldo | F1: Folio
A2: 45966 | B2: SPEI RECIBIDOHSBC/0177980786 021 0051125Arturo de Cardenas | D2: 900 | E2: 64403.53
A3: 45966 | B3: PAGO CUENTA DE TERCERO/ 0036729331 BNET 2723378160 tapetes | D3: 1000 | E3: 63503.53
A4: 45966 | B4: PAGO CUENTA DE TERCERO/ 0039336585 BNET 2960808008 lavasnart | D4: 1000 | E4: 62503.53
A5: 45966 | B5: SPEI RECIBIDOSANTANDER/0175746190 014 3422688ALEJANDRO DOMINGUEZ | D5: 850 | E5: 61503.53
A6: 45966 | B6: DEPOSITO EN EFECTIVO/0015175 | D6: 10850 | E6: 60653.53
A7: 45966 | B7: TRASPASO CUENTAS PROPIAS/ 1324865757 CUENTA: 0120217220 BNET | C7: 70000 | E7: 49803.53
A8: 45966 | B8: TRASPASO CUENTAS PROPIAS/ 1324814778 CUENTA: 0125721601 BNET | D8: 50032.82 | E8: 119803.53
A9: 45966 | B9: PAGO CUENTA DE TERCERO/ 0050922952 BNET 1599726333 Ricardo Benitez | D9: 701 | E9: 69770.71
A10: 45966 | B10: IVA COM. VENTAS CREDITO/174771412 TERMINALES PUNTO DE VENTA | C10: 4.32 | E10: 69069.71
A11: 45966 | B11: COMISION VENTAS CREDITO/174771412 TERMINALES PUNTO DE VENTA | C11: 26.97 | E11: 69074.03
A12: 45966 | B12: VENTAS CREDITO/144771412 TERMINALES PUNTO DE VENTA | D12: 1199 | E12: 69101
A13: 45967 | B13: PAGO CUENTA DE TERCERO/ 0053933298 BNET 1536166349 Frida Ruiz PROPINA | D13: 100 | E13: 95616.92
A14: 45967 | B14: SPEI RECIBIDOMercado Pago/0183385533 722 1820119Limpieza sillón | D14: 1000 | E14: 95516.92
A15: 45967 | B15: PAGO CUENTA DE TERCERO/ 0047245315 BNET 1570646977 Transf a Lavasmart | D15: 1000 | E15: 94516.92
A16: 45967 | B16: PAGO CUENTA DE TERCERO/ 0020194086 BNET 1243083357 lavado sillones | D16: 1650 | E16: 93516.92
A17: 45967 | B17: SPEI RECIBIDOSCOTIABANK/0182304620 044 0000001pago por lavado de sala | D17: 750 | E17: 91866.92
A18: 45967 | B18: PAGO CUENTA DE TERCERO/ 0084590834 BNET 2752418789 lago pom261 | D18: 950 | E18: 91116.92
A19: 45967 | B19: DEPOSITO EFECTIVO PRACTIC/******5546 NOV06 12:21 PRAC 7490 FOLIO:1123 | D19: 10900 | E19: 90166.92 | F19: 0-18743
A20: 45967 | B20: SPEI RECIBIDOBANAMEX/0181875752 002 0061125Dos alfombras | D20: 1450 | E20: 79266.92
A21: 45967 | B21: PAGO CUENTA DE TERCERO/ 0090425130 BNET 0469938362 Yo | D21: 1000 | E21: 77816.92
A22: 45967 | B22: PAGO CUENTA DE TERCERO/ 0072858732 BNET 0446170188 tapetes | D22: 1200 | E22: 76816.92
A23: 45967 | B23: PAGO CUENTA DE TERCERO/ 0081718014 BNET 0125305241 pago | D23: 3950 | E23: 75616.92
A24: 45967 | B24: SPEI RECIBIDOBANORTE/0180649497 072 0251106Sin informaci n | D24: 300 | E24: 71666.92
A25: 45967 | B25: IVA COM. VENTAS CREDITO/174771419 TERMINALES PUNTO DE VENTA | C25: 9.72 | E25: 71366.92
A26: 45967 | B26: COMISION VENTAS CREDITO/174771419 TERMINALES PUNTO DE VENTA | C26: 60.75 | E26: 71376.64
A27: 45967 | B27: VENTAS CREDITO/144771419 TERMINALES PUNTO DE VENTA | D27: 2700 | E27: 71437.39
A28: 45967 | B28: IVA COM. VENTAS CREDITO/174764991 TERMINALES PUNTO DE VENTA | C28: 8.64 | E28: 68737.39
A29: 45967 | B29: COMISION VENTAS CREDITO/174764991 TERMINALES PUNTO DE VENTA | C29: 54 | E29: 68746.03
A30: 45967 | B30: VENTAS CREDITO/144764991 TERMINALES PUNTO DE VENTA | D30: 2400 | E30: 68800.03
A31: 45967 | B31: IVA COM. VENTAS DEBITO/174895225 TERMINALES PUNTO DE VENTA | C31: 4.32 | E31: 66400.03
A32: 45967 | B32: COMISION VENTAS DEBITO/174895225 TERMINALES PUNTO DE VENTA | C32: 27 | E32: 66404.35
A33: 45967 | B33: VENTAS DEBITO/144895225 TERMINALES PUNTO DE VENTA | D33: 1200 | E33: 66431.35
A34: 45967 | B34: IVA COM. VENTAS CREDITO/174895225 TERMINALES PUNTO DE VENTA | C34: 3.06 | E34: 65231.35
A35: 45967 | B35: COMISION VENTAS CREDITO/174895225 TERMINALES PUNTO DE VENTA | C35: 19.12 | E35: 65234.41
A36: 45967 | B36: VENTAS CREDITO/144895225 TERMINALES PUNTO DE VENTA | D36: 850 | E36: 65253.53
A37: 45968 | B37: SPEI RECIBIDOBANCOPPEL/0188955951 137 9093087Transf. a lavasmart | D37: 1200 | E37: 128366.85
A38: 45968 | B38: SPEI RECIBIDOINBURSA/0188893024 036 2025110Mónica Franco | D38: 1200 | E38: 127166.85
A39: 45968 | B39: DEPOSITO EN EFECTIVO/0015230 | D39: 14295 | E39: 125966.85
A40: 45968 | B40: PAGO CUENTA DE TERCERO/ 0081156146 BNET 1549512538 servicio tapete | D40: 600 | E40: 111671.85
A41: 45968 | B41: PAGO CUENTA DE TERCERO/ 0029412895 BNET 2729518533 Transf a LAVASMART | D41: 750 | E41: 111071.85
A42: 45968 | B42: IVA COM. VENTAS CREDITO/174895225 TERMINALES PUNTO DE VENTA | C42: 5.76 | E42: 110321.85
A43: 45968 | B43: COMISION VENTAS CREDITO/174895225 TERMINALES PUNTO DE VENTA | C43: 36 | E43: 110327.61
A44: 45968 | B44: VENTAS CREDITO/144895225 TERMINALES PUNTO DE VENTA | D44: 1600 | E44: 110363.61
A45: 45968 | B45: IVA COM. VENTAS DEBITO/174771412 TERMINALES PUNTO DE VENTA | C45: 7.2 | E45: 108763.61
A46: 45968 | B46: COMISION VENTAS DEBITO/174771412 TERMINALES PUNTO DE VENTA | C46: 45 | E46: 108770.81
A47: 45968 | B47: VENTAS DEBITO/144771412 TERMINALES PUNTO DE VENTA | D47: 2000 | E47: 108815.81
A48: 45968 | B48: IVA COM. VENTAS DEBITO/174764975 TERMINALES PUNTO DE VENTA | C48: 3.24 | E48: 106815.81
A49: 45968 | B49: COMISION VENTAS DEBITO/174764975 TERMINALES PUNTO DE VENTA | C49: 20.24 | E49: 106819.05
A50: 45968 | B50: VENTAS DEBITO/144764975 TERMINALES PUNTO DE VENTA | D50: 899.99 | E50: 106839.29
A51: 45968 | B51: IVA COM. VENTAS CREDITO/174895225 TERMINALES PUNTO DE VENTA | C51: 9.72 | E51: 105939.3
A52: 45968 | B52: COMISION VENTAS CREDITO/174895225 TERMINALES PUNTO DE VENTA | C52: 60.75 | E52: 105949.02
A53: 45968 | B53: VENTAS CREDITO/144895225 TERMINALES PUNTO DE VENTA | D53: 2700 | E53: 106009.77
A54: 45968 | B54: IVA COM. VENTAS DEBITO/174771412 TERMINALES PUNTO DE VENTA | C54: 7.56 | E54: 103309.77
A55: 45968 | B55: COMISION VENTAS DEBITO/174771412 TERMINALES PUNTO DE VENTA | C55: 47.22 | E55: 103317.33
A56: 45968 | B56: VENTAS DEBITO/144771412 TERMINALES PUNTO DE VENTA | D56: 2099 | E56: 103364.55
A57: 45968 | B57: IVA COM. VENTAS DEBITO/174764991 TERMINALES PUNTO DE VENTA | C57: 7.2 | E57: 101265.55
A58: 45968 | B58: COMISION VENTAS DEBITO/174764991 TERMINALES PUNTO DE VENTA | C58: 45 | E58: 101272.75
A59: 45968 | B59: VENTAS DEBITO/144764991 TERMINALES PUNTO DE VENTA | D59: 2000 | E59: 101317.75
A60: 45968 | B60: IVA COM. VENTAS CREDITO/174764991 TERMINALES PUNTO DE VENTA | C60: 4.32 | E60: 99317.75
A61: 45968 | B61: COMISION VENTAS CREDITO/174764991 TERMINALES PUNTO DE VENTA | C61: 27 | E61: 99322.07
A62: 45968 | B62: VENTAS CREDITO/144764991 TERMINALES PUNTO DE VENTA | D62: 1200 | E62: 99349.07
A63: 45968 | B63: IVA COM. VENTAS CREDITO/174764975 TERMINALES PUNTO DE VENTA | C63: 9.36 | E63: 98149.07
A64: 45968 | B64: COMISION VENTAS CREDITO/174764975 TERMINALES PUNTO DE VENTA | C64: 58.49 | E64: 98158.43
A65: 45968 | B65: VENTAS CREDITO/144764975 TERMINALES PUNTO DE VENTA | D65: 2600 | E65: 98216.92
A66: 45969 | B66: SPEI RECIBIDOBANAMEX/0195373633 002 0081125pago | D66: 850 | E66: 135365.85
A67: 45969 | B67: PAGO CUENTA DE TERCERO/ 0070070850 BNET 2682635356 servicio | D67: 750 | E67: 134515.85
A68: 45969 | B68: PAGO CUENTA DE TERCERO/ 0065323032 BNET 1556542417 Pilar Navarro | D68: 750 | E68: 133765.85
A69: 45969 | B69: SPEI RECIBIDOHSBC/0194520485 021 0000007Transferencia SPEI | D69: 899 | E69: 133015.85
A70: 45969 | B70: SPEI RECIBIDOSANTANDER/0194300094 014 4230794DE PAULA PIMENTEL | D70: 1200 | E70: 132116.85
A71: 45969 | B71: SPEI RECIBIDOalbo/0194208239 721 0081125Transferencia | D71: 750 | E71: 130916.85
A72: 45969 | B72: PAGO CUENTA DE TERCERO/ 0019894285 BNET 1524422904 Pago Christopher L | D72: 1200 | E72: 130166.85
A73: 45969 | B73: SPEI RECIBIDOHSBC/0193201538 021 0081125Tapete | D73: 600 | E73: 128966.85
A74: 45970 | B74: SPEI RECIBIDOSANTANDER/0198976027 014 9416248TRANSFERENCIA A LIMPIEZA DE SI | D74: 850 | E74: 139664.85
A75: 45970 | B75: SPEI RECIBIDOBANORTE/0198732799 072 0251109Sin informaci n | D75: 750 | E75: 138814.85
A76: 45970 | B76: PAGO CUENTA DE TERCERO/ 0077507083 BNET 1543183368 lavado de alfombra | D76: 900 | E76: 138064.85
... A85: 45971 | B85: SPEI RECIBIDONU MEXICO/0102156445 638 0101125Transferencia | D85: 1100 | E85: 165783.61
A86: 45971 | B86: IVA COM. VENTAS DEBITO/174771403 TERMINALES PUNTO DE VENTA | C86: 3.06 | E86: 164683.61
A87: 45971 | B87: COMISION VENTAS DEBITO/174771403 TERMINALES PUNTO DE VENTA | C87: 19.12 | E87: 164686.67
A88: 45971 | B88: VENTAS DEBITO/144771403 TERMINALES PUNTO DE VENTA | D88: 850 | E88: 164705.79
A89: 45971 | B89: IVA COM. VENTAS CREDITO/174764975 TERMINALES PUNTO DE VENTA | C89: 7.2 | E89: 163855.79
A90: 45971 | B90: COMISION VENTAS CREDITO/174764975 TERMINALES PUNTO DE VENTA | C90: 45 | E90: 163862.99
A91: 45971 | B91: VENTAS CREDITO/144764975 TERMINALES PUNTO DE VENTA | D91: 2000 | E91: 163907.99
A92: 45971 | B92: IVA COM. VENTAS DEBITO/174895225 TERMINALES PUNTO DE VENTA | C92: 3.06 | E92: 161907.99
A93: 45971 | B93: COMISION VENTAS DEBITO/174895225 TERMINALES PUNTO DE VENTA | C93: 19.12 | E93: 161911.05
A94: 45971 | B94: VENTAS DEBITO/144895225 TERMINALES PUNTO DE VENTA | D94: 850 | E94: 161930.17
A95: 45971 | B95: IVA COM. VENTAS CREDITO/174895225 TERMINALES PUNTO DE VENTA | C95: 6.3 | E95: 161080.17
A96: 45971 | B96: COMISION VENTAS CREDITO/174895225 TERMINALES PUNTO DE VENTA | C96: 39.37 | E96: 161086.47
A97: 45971 | B97: VENTAS CREDITO/144895225 TERMINALES PUNTO DE VENTA | D97: 1750 | E97: 161125.84
A98: 45971 | B98: IVA COM. VENTAS DEBITO/174771419 TERMINALES PUNTO DE VENTA | C98: 10.8 | E98: 159375.84
A99: 45971 | B99: COMISION VENTAS DEBITO/174771419 TERMINALES PUNTO DE VENTA | C99: 67.5 | E99: 159386.64
A100: 45971 | B100: VENTAS DEBITO/144771419 TERMINALES PUNTO DE VENTA | D100: 3000 | E100: 159454.14
A101: 45971 | B101: IVA COM. VENTAS CREDITO/174764991 TERMINALES PUNTO DE VENTA | C101: 12.96 | E101: 156454.14
A102: 45971 | B102: COMISION VENTAS CREDITO/174764991 TERMINALES PUNTO DE VENTA | C102: 80.99 | E102: 156467.1
A103: 45971 | B103: VENTAS CREDITO/144764991 TERMINALES PUNTO DE VENTA | D103: 3600 | E103: 156548.09
A104: 45971 | B104: IVA COM. VENTAS CREDITO/174771412 TERMINALES PUNTO DE VENTA | C104: 5.76 | E104: 152948.09
A105: 45971 | B105: COMISION VENTAS CREDITO/174771412 TERMINALES PUNTO DE VENTA | C105: 36 | E105: 152953.85
A106: 45971 | B106: VENTAS CREDITO/144771412 TERMINALES PUNTO DE VENTA | D106: 1600 | E106: 152989.85
A107: 45971 | B107: IVA COM. VENTAS CREDITO/174764975 TERMINALES PUNTO DE VENTA | C107: 3.24 | E107: 151389.85
A108: 45971 | B108: COMISION VENTAS CREDITO/174764975 TERMINALES PUNTO DE VENTA | C108: 20.24 | E108: 151393.09
...

Sheet cat
K2: Tipos de incidencia
J3: 1 | K3: Falta evidencia (nota de venta) | L3: Pendiente
J4: 2 | K4: Nota de venta ilegible | L4: En progreso
J5: 3 | K5: Falta comprobante de pago | L5: Revisar nuevamente
J6: 4 | K6: Comprobante incorrecto | L6: Resuelto
J7: 5 | K7: Método de pago incorrecto
J8: 6 | K8: Discrepancia entre reporte y deposito
J9: 7 | K9: Falta de carga de evidencia
K11: Otro

Sheet Conciliacion_Tarjetas
A1: Fecha | B1: Folio | C1: Cliente | D1: Servicio (s) | E1: Monto | F1: 🧾 Recibo | G1: afiliación | H1: 📦 # Lote | I1: 🔍 Observaciones
A2: 45990.042 | B2: 0-18045 | C2: Graciela Mayorga | D2: Sala 2 Plazas | E2: 850 | F2: SI | G2: 4771419 | H2: 14
A3: 45990.042 | B3: 0-18046 | C3: Ramón Quijano | D3: sillon 3 plazas | E3: 1070 | F3: SI | G3: 4771419 | H3: 14
A4: 45990.042 | B4: 0-18896 | C4: Belem de La Fuente | D4: Colchón king + sillon reclinable | E4: 1400 | F4: SI | G4: 4764954 | H4: 190
A5: 45990.042 | B5: 0-18897 | C5: Marisela Aguilera | D5: sala en L para 8 personas + sofá cama | E5: 1800
A6: 45990.042 | B6: 0-18319 | C6: Guadalupe Hernandez | D6: 3 colchones | E6: 1500 | F6: SI | G6: 4895225 | H6: 15
A7: 45990.042 | B7: 0-17855 | C7: Bernardette Espin | D7: Auto Chico + sala 5 plazas + tapete 1.6 x 2.3 | E7: 1850 | F7: SI | G7: 4895225 | H7: 86
A8: 45991.042 | B8: 0-17857 | C8: Antonio Aranda | D8: Hyundai Onix | E8: 900 | F8: SI | G8: 4895225 | H8: 87
A9: 45991.042 | B9: 0-18323 | C9: Adrían León | D9: 2 tapetes + alfombra | E9: 2000
A10: 45990.042 | B10: 0-18635 | C10: Paz Flores | D10: Sala 3 piezas | E10: 850
A11: 45990.042 | B11: 0-18791 | C11: Adriana Guerrero | D11: sofá 3 plazas | E11: 750
A12: 45991.042 | B12: 0-18486 | C12: Antonio Prado | D12: sala 3 piezas | E12: 850
A13: 45991.042 | B13: 0-18488 | C13: Patricia Ojeda | D13: camioneta chica+ 6 sillas | E13: 1300
A14: 45991.042 | B14: 0-18639 | C14: Carlos Sánchez | D14: Auto chico | E14: 900
A15: 45991.042 | B15: 0-18640 | C15: Heriberto Rodríguez | D15: Sala L | E15: 950
A16: 45991.042 | B16: 0-18792 | C16: María Eugenia Anzuresz | D16: 4 sillas + 3 colchones (queen y king) + Sala de 3 piezas + tapete 1x1.80 | E16: 3200
A17: 45992.042 | B17: 0-17860 | C17: Rosa Campos | D17: Sala L + sillón 3 plazas | E17: 1250
A18: 45992.042 | B18: 0-17861 | C18: Elizabeth Lozada | D18: Sala 2 piezas + 2 tapetes 1.8x1.20 | E18: 1400
A19: 45992.042 | B19: 0-17862 | C19: Mónica Jiménez | D19: Vento | E19: 900
A20: 45992.042 | B20: 0-18299 | C20: Norma Rojas | D20: Sala L+ 5 cojines decorativos | E20: 850
... A41: 45994.042 | B41: 0-18499 | C41: Ana Camarena | D41: 6 tapetes de 2x1 y 4 sillas | E41: 3000

Sheet Cierres_Lotes

Sheet 📢 Bitácora_Hallazgos
A2: 📅 Fecha Reporte | B2: 🚨 Tipo de Hallazgo | C2: 📝 Folio | D2: ⚠️ Urgencia | E2: 💬 Descripción Detallada | F2: 🚧 Estado | G2: 💡 Resolución / Respuesta
A3: 45982 | B3: Discrepancia entre reporte y deposito | C3: 0-18051 | D3: 🔥 ALTA | E3: El pago no está en el banco | F3: Pendiente | H3: <- Ejemplo (borrar)
A4: 45980 | B4: Discrepancia entre reporte y deposito | C4: 0-18752 | D4: 🔥 ALTA | E4: Es un lavado de sala el costo es de $1300 y en el banco solo hay $950 | F4: Pendiente
A5: 45977 | B5: Falta comprobante de pago | C5: 0-18897 | D5: 🔥 ALTA | F5: Pendiente
A6: 45977 | B6: Falta comprobante de pago | C6: 0-18157 | D6: 🔥 ALTA | F6: Pendiente

Sheet totales
A1: Fecha | B1: Transferencia | C1: Banco
A2: 45658 | B2: =SUMIFS(Conciliacion_Transferencias!$F$2:$F1000,Conciliacion_Transferencias!$A$2:$A1000,$A2) -> 0
A3: 45659 | B3: =SUMIFS(Conciliacion_Transferencias!$F$2:$F1000,Conciliacion_Transferencias!$A$2:$A1000,$A3) -> 0
A4: 45660 | B4: =SUMIFS(Conciliacion_Transferencias!$F$2:$F1000,Conciliacion_Transferencias!$A$2:$A1000,$A4) -> 0
A5: 45661 | B5: =SUMIFS(Conciliacion_Transferencias!$F$2:$F1000,Conciliacion_Transferencias!$A$2:$A1000,$A5) -> 0
A6: 45662 | B6: =SUMIFS(Conciliacion_Transferencias!$F$2:$F1000,Conciliacion_Transferencias!$A$2:$A1000,$A6) -> 0
A7: 45663 | B7: =SUMIFS(Conciliacion_Transferencias!$F$2:$F1000,Conciliacion_Transferencias!$A$2:$A1000,$A7) -> 0
A8: 45664 | B8: =SUMIFS(Conciliacion_Transferencias!$F$2:$F1000,Conciliacion_Transferencias!$A$2:$A1000,$A8) -> 0
A9: 45665 | B9: =SUMIFS(Conciliacion_Transferencias!$F$2:$F1000,Conciliacion_Transferencias!$A$2:$A1000,$A9) -> 0
A10: 45666 | B10: =SUMIFS(Conciliacion_Transferencias!$F$2:$F1000,Conciliacion_Transferencias!$A$2:$A1000,$A10) -> 0
A11: 45667 | B11: =SUMIFS(Conciliacion_Transferencias!$F$2:$F1000,Conciliacion_Transferencias!$A$2:$A1000,$A11) -> 0
A12: 45668 | B12: =SUMIFS(Conciliacion_Transferencias!$F$2:$F1000,Conciliacion_Transferencias!$A$2:$A1000,$A12) -> 0
A13: 45669 | B13: =SUMIFS(Conciliacion_Transferencias!$F$2:$F1000,Conciliacion_Transferencias!$A$2:$A1000,$A13) -> 0
A14: 45670 | B14: =SUMIFS(Conciliacion_Transferencias!$F$2:$F1000,Conciliacion_Transferencias!$A$2:$A1000,$A14) -> 0
A15: 45671 | B15: =SUMIFS(Conciliacion_Transferencias!$F$2:$F1000,Conciliacion_Transferencias!$A$2:$A1000,$A15) -> 0
A16: 45672 | B16: =SUMIFS(Conciliacion_Transferencias!$F$2:$F1000,Conciliacion_Transferencias!$A$2:$A1000,$A16) -> 0
A17: 45673 | B17: =SUMIFS(Conciliacion_Transferencias!$F$2:$F1000,Conciliacion_Transferencias!$A$2:$A1000,$A17) -> 0
A18: 45674 | B18: =SUMIFS(Conciliacion_Transferencias!$F$2:$F1000,Conciliacion_Transferencias!$A$2:$A1000,$A18) -> 0
A19: 45675 | B19: =SUMIFS(Conciliacion_Transferencias!$F$2:$F1000,Conciliacion_Transferencias!$A$2:$A1000,$A19) -> 0
A20: 45676 | B20: =SUMIFS(Conciliacion_Transferencias!$F$2:$F1000,Conciliacion_Transferencias!$A$2:$A1000,$A20) -> 0
A21: 45677 | B21: =SUMIFS(Conciliacion_Transferencias!$F$2:$F1000,Conciliacion_Transferencias!$A$2:$A1000,$A21) -> 0
A22: 45678 | B22: =SUMIFS(Conciliacion_Transferencias!$F$2:$F1000,Conciliacion_Transferencias!$A$2:$A1000,$A22) -> 0
A23: 45679 | B23: =SUMIFS(Conciliacion_Transferencias!$F$2:$F1000,Conciliacion_Transferencias!$A$2:$A1000,$A23) -> 0
A24: 45680 | B24: =SUMIFS(Conciliacion_Transferencias!$F$2:$F1000,Conciliacion_Transferencias!$A$2:$A1000,$A24) -> 0
A25: 45681 | B25: =SUMIFS(Conciliacion_Transferencias!$F$2:$F1000,Conciliacion_Transferencias!$A$2:$A1000,$A25) -> 0
A26: 45682 | B26: =SUMIFS(Conciliacion_Transferencias!$F$2:$F1000,Conciliacion_Transferencias!$A$2:$A1000,$A26) -> 0
A27: 45683 | B27: =SUMIFS(Conciliacion_Transferencias!$F$2:$F1000,Conciliacion_Transferencias!$A$2:$A1000,$A27) -> 0
A28: 45684 | B28: =SUMIFS(Conciliacion_Transferencias!$F$2:$F1000,Conciliacion_Transferencias!$A$2:$A1000,$A28) -> 0
A29: 45685 | B29: =SUMIFS(Conciliacion_Transferencias!$F$2:$F1000,Conciliacion_Transferencias!$A$2:$A1000,$A29) -> 0
A30: 45686 | B30: =SUMIFS(Conciliacion_Transferencias!$F$2:$F1000,Conciliacion_Transferencias!$A$2:$A1000,$A30) -> 0
A31: 45687 | B31: =SUMIFS(Conciliacion_Transferencias!$F$2:$F1000,Conciliacion_Transferencias!$A$2:$A1000,$A31) -> 0
A32: 45688 | B32: =SUMIFS(Conciliacion_Transferencias!$F$2:$F1000,Conciliacion_Transferencias!$A$2:$A1000,$A32) -> 0
A33: 45689 | B33: =SUMIFS(Conciliacion_Transferencias!$F$2:$F1000,Conciliacion_Transferencias!$A$2:$A1000,$A33) -> 0
A34: 45690 | B34: =SUMIFS(Conciliacion_Transferencias!$F$2:$F1000,Conciliacion_Transferencias!$A$2:$A1000,$A34) -> 0
A35: 45691 | B35: =SUMIFS(Conciliacion_Transferencias!$F$2:$F1000,Conciliacion_Transferencias!$A$2:$A1000,$A35) -> 0
A36: 45692 | B36: =SUMIFS(Conciliacion_Transferencias!$F$2:$F1000,Conciliacion_Transferencias!$A$2:$A1000,$A36) -> 0
A37: 45693 | B37: =SUMIFS(Conciliacion_Transferencias!$F$2:$F1000,Conciliacion_Transferencias!$A$2:$A1000,$A37) -> 0
A38: 45694 | B38: =SUMIFS(Conciliacion_Transferencias!$F$2:$F1000,Conciliacion_Transferencias!$A$2:$A1000,$A38) -> 0
A39: 45695 | B39: =SUMIFS(Conciliacion_Transferencias!$F$2:$F1000,Conciliacion_Transferencias!$A$2:$A1000,$A39) -> 0
A40: 45696 | B40: =SUMIFS(Conciliacion_Transferencias!$F$2:$F1000,Conciliacion_Transferencias!$A$2:$A1000,$A40) -> 0
A41: 45697 | B41: =SUMIFS(Conciliacion_Transferencias!$F$2:$F1000,Conciliacion_Transferencias!$A$2:$A1000,$A41) -> 0
A42: 45698 | B42: =SUMIFS(Conciliacion_Transferencias!$F$2:$F1000,Conciliacion_Transferencias!$A$2:$A1000,$A42) -> 0
A43: 45699 | B43: =SUMIFS(Conciliacion_Transferencias!$F$2:$F1000,Conciliacion_Transferencias!$A$2:$A1000,$A43) -> 0
A44: 45700 | B44: =SUMIFS(Conciliacion_Transferencias!$F$2:$F1000,Conciliacion_Transferencias!$A$2:$A1000,$A44) -> 0
A45: 45701 | B45: =SUMIFS(Conciliacion_Transferencias!$F$2:$F1000,Conciliacion_Transferencias!$A$2:$A1000,$A45) -> 0
A46: 45702 | B46: =SUMIFS(Conciliacion_Transferencias!$F$2:$F1000,Conciliacion_Transferencias!$A$2:$A1000,$A46) -> 0
A47: 45703 | B47: =SUMIFS(Conciliacion_Transferencias!$F$2:$F1000,Conciliacion_Transferencias!$A$2:$A1000,$A47) -> 0
A48: 45704 | B48: =SUMIFS(Conciliacion_Transferencias!$F$2:$F1000,Conciliacion_Transferencias!$A$2:$A1000,$A48) -> 0
A49: 45705 | B49: =SUMIFS(Conciliacion_Transferencias!$F$2:$F1000,Conciliacion_Transferencias!$A$2:$A1000,$A49) -> 0
A50: 45706 | B50: =SUMIFS(Conciliacion_Transferencias!$F$2:$F1000,Conciliacion_Transferencias!$A$2:$A1000,$A50) -> 0
A51: 45707 | B51: =SUMIFS(Conciliacion_Transferencias!$F$2:$F1000,Conciliacion_Transferencias!$A$2:$A1000,$A51) -> 0
A52: 45708 | B52: =SUMIFS(Conciliacion_Transferencias!$F$2:$F1000,Conciliacion_Transferencias!$A$2:$A1000,$A52) -> 0
A53: 45709 | B53: =SUMIFS(Conciliacion_Transferencias!$F$2:$F1000,Conciliacion_Transferencias!$A$2:$A1000,$A53) -> 0
A54: 45710 | B54: =SUMIFS(Conciliacion_Transferencias!$F$2:$F1000,Conciliacion_Transferencias!$A$2:$A1000,$A54) -> 0
A55: 45711 | B55: =SUMIFS(Conciliacion_Transferencias!$F$2:$F1000,Conciliacion_Transferencias!$A$2:$A1000,$A55) -> 0
A56: 45712 | B56: =SUMIFS(Conciliacion_Transferencias!$F$2:$F1000,Conciliacion_Transferencias!$A$2:$A1000,$A56) -> 0
A57: 45713 | B57: =SUMIFS(Conciliacion_Transferencias!$F$2:$F1000,Conciliacion_Transferencias!$A$2:$A1000,$A57) -> 0
A58: 45714 | B58: =SUMIFS(Conciliacion_Transferencias!$F$2:$F1000,Conciliacion_Transferencias!$A$2:$A1000,$A58) -> 0
A59: 45715 | B59: =SUMIFS(Conciliacion_Transferencias!$F$2:$F1000,Conciliacion_Transferencias!$A$2:$A1000,$A59) -> 0
A60: 45716 | B60: =SUMIFS(Conciliacion_Transferencias!$F$2:$F1000,Conciliacion_Transferencias!$A$2:$A1000,$A60) -> 0
A61: 45717 | B61: =SUMIFS(Conciliacion_Transferencias!$F$2:$F1000,Conciliacion_Transferencias!$A$2:$A1000,$A61) -> 0
A62: 45718 | B62: =SUMIFS(Conciliacion_Transferencias!$F$2:$F1000,Conciliacion_Transferencias!$A$2:$A1000,$A62) -> 0
A63: 45719 | B63: =SUMIFS(Conciliacion_Transferencias!$F$2:$F1000,Conciliacion_Transferencias!$A$2:$A1000,$A63) -> 0
A64: 45720 | B64: =SUMIFS(Conciliacion_Transferencias!$F$2:$F1000,Conciliacion_Transferencias!$A$2:$A1000,$A64) -> 0
A65: 45721 | B65: =SUMIFS(Conciliacion_Transferencias!$F$2:$F1000,Conciliacion_Transferencias!$A$2:$A1000,$A65) -> 0
A66: 45722 | B66: =SUMIFS(Conciliacion_Transferencias!$F$2:$F1000,Conciliacion_Transferencias!$A$2:$A1000,$A66) -> 0
A67: 45723 | B67: =SUMIFS(Conciliacion_Transferencias!$F$2:$F1000,Conciliacion_Transferencias!$A$2:$A1000,$A67) -> 0
A68: 45724 | B68: =SUMIFS(Conciliacion_Transferencias!$F$2:$F1000,Conciliacion_Transferencias!$A$2:$A1000,$A68) -> 0
A69: 45725 | B69: =SUMIFS(Conciliacion_Transferencias!$F$2:$F1000,Conciliacion_Transferencias!$A$2:$A1000,$A69) -> 0
A70: 45726 | B70: =SUMIFS(Conciliacion_Transferencias!$F$2:$F1000,Conciliacion_Transferencias!$A$2:$A1000,$A70) -> 0
A71: 45727 | B71: =SUMIFS(Conciliacion_Transferencias!$F$2:$F1000,Conciliacion_Transferencias!$A$2:$A1000,$A71) -> 0
A72: 45728 | B72: =SUMIFS(Conciliacion_Transferencias!$F$2:$F1000,Conciliacion_Transferencias!$A$2:$A1000,$A72) -> 0
A73: 45729 | B73: =SUMIFS(Conciliacion_Transferencias!$F$2:$F1000,Conciliacion_Transferencias!$A$2:$A1000,$A73) -> 0
A74: 45730 | B74: =SUMIFS(Conciliacion_Transferencias!$F$2:$F1000,Conciliacion_Transferencias!$A$2:$A1000,$A74) -> 0
A75: 45731 | B75: =SUMIFS(Conciliacion_Transferencias!$F$2:$F1000,Conciliacion_Transferencias!$A$2:$A1000,$A75) -> 0
A76: 45732 | B76: =SUMIFS(Conciliacion_Transferencias!$F$2:$F1000,Conciliacion_Transferencias!$A$2:$A1000,$A76) -> 0
A77: 45733 | B77: =SUMIFS(Conciliacion_Transferencias!$F$2:$F1000,Conciliacion_Transferencias!$A$2:$A1000,$A77) -> 0
A78: 45734 | B78: =SUMIFS(Conciliacion_Transferencias!$F$2:$F1000,Conciliacion_Transferencias!$A$2:$A1000,$A78) -> 0
A79: 45735 | B79: =SUMIFS(Conciliacion_Transferencias!$F$2:$F1000,Conciliacion_Transferencias!$A$2:$A1000,$A79) -> 0
A80: 45736 | B80: =SUMIFS(Conciliacion_Transferencias!$F$2:$F1000,Conciliacion_Transferencias!$A$2:$A1000,$A80) -> 0
A81: 45737 | B81: =SUMIFS(Conciliacion_Transferencias!$F$2:$F1000,Conciliacion_Transferencias!$A$2:$A1000,$A81) -> 0
A82: 45738 | B82: =SUMIFS(Conciliacion_Transferencias!$F$2:$F1000,Conciliacion_Transferencias!$A$2:$A1000,$A82) -> 0
A83: 45739 | B83: =SUMIFS(Conciliacion_Transferencias!$F$2:$F1000,Conciliacion_Transferencias!$A$2:$A1000,$A83) -> 0
A84: 45740 | B84: =SUMIFS(Conciliacion_Transferencias!$F$2:$F1000,Conciliacion_Transferencias!$A$2:$A1000,$A84) -> 0
A85: 45741 | B85: =SUMIFS(Conciliacion_Transferencias!$F$2:$F1000,Conciliacion_Transferencias!$A$2:$A1000,$A85) -> 0
A86: 45742 | B86: =SUMIFS(Conciliacion_Transferencias!$F$2:$F1000,Conciliacion_Transferencias!$A$2:$A1000,$A86) -> 0
A87: 45743 | B87: =SUMIFS(Conciliacion_Transferencias!$F$2:$F1000,Conciliacion_Transferencias!$A$2:$A1000,$A87) -> 0
A88: 45744 | B88: =SUMIFS(Conciliacion_Transferencias!$F$2:$F1000,Conciliacion_Transferencias!$A$2:$A1000,$A88) -> 0
A89: 45745 | B89: =SUMIFS(Conciliacion_Transferencias!$F$2:$F1000,Conciliacion_Transferencias!$A$2:$A1000,$A89) -> 0
A90: 45746 | B90: =SUMIFS(Conciliacion_Transferencias!$F$2:$F1000,Conciliacion_Transferencias!$A$2:$A1000,$A90) -> 0
A91: 45747 | B91: =SUMIFS(Conciliacion_Transferencias!$F$2:$F1000,Conciliacion_Transferencias!$A$2:$A1000,$A91) -> 0
A92: 45748 | B92: =SUMIFS(Conciliacion_Transferencias!$F$2:$F1000,Conciliacion_Transferencias!$A$2:$A1000,$A92) -> 0
A93: 45749 | B93: =SUMIFS(Conciliacion_Transferencias!$F$2:$F1000,Conciliacion_Transferencias!$A$2:$A1000,$A93) -> 0
A94: 45750 | B94: =SUMIFS(Conciliacion_Transferencias!$F$2:$F1000,Conciliacion_Transferencias!$A$2:$A1000,$A94) -> 0
A95: 45751 | B95: =SUMIFS(Conciliacion_Transferencias!$F$2:$F1000,Conciliacion_Transferencias!$A$2:$A1000,$A95) -> 0
A96: 45752 | B96: =SUMIFS(Conciliacion_Transferencias!$F$2:$F1000,Conciliacion_Transferencias!$A$2:$A1000,$A96) -> 0
A97: 45753 | B97: =SUMIFS(Conciliacion_Transferencias!$F$2:$F1000,Conciliacion_Transferencias!$A$2:$A1000,$A97) -> 0
A98: 45754 | B98: =SUMIFS(Conciliacion_Transferencias!$F$2:$F1000,Conciliacion_Transferencias!$A$2:$A1000,$A98) -> 0
A99: 45755 | B99: =SUMIFS(Conciliacion_Transferencias!$F$2:$F1000,Conciliacion_Transferencias!$A$2:$A1000,$A99) -> 0
A100: 45756 | B100: =SUMIFS(Conciliacion_Transferencias!$F$2:$F1000,Conciliacion_Transferencias!$A$2:$A1000,$A100) -> 0
...

Sheet 📝 Bitácora_Cambios
A1: Timestamp | B1: Folio | C1: Campo Modificado | D1: Valor Anterior | E1: Valor Nuevo
A2: 45984.941 | B2: 0-18758 | C2: Banco: → SCOTIABANK | D2: Monto: 950; Banco: | E2: Monto: 950; Banco: SCOTIABANK
A3: 45984.941 | B3: 0-18759 | C3: Banco: → BANCOMER | D3: Monto: 2300; Banco: | E3: Monto: 2300; Banco: BANCOMER
A4: 45984.941 | B4: 0-18607 | C4: Banco: → BANORTE | D4: Monto: 1400; Banco: | E4: Monto: 1400; Banco: BANORTE
A5: 45984.941 | B5: 0-18609 | C5: Banco: → SANTANDER | D5: Monto: 1250; Banco: | E5: Monto: 1250; Banco: SANTANDER
A6: 45984.941 | B6: 0-18610 | C6: Banco: → NU-MORADO | D6: Monto: 900; Banco: | E6: Monto: 900; Banco: NU-MORADO
A7: 45984.941 | B7: 0-18016 | C7: Banco: → SANTANDER | D7: Monto: 700; Banco: | E7: Monto: 700; Banco: SANTANDER
A8: 45986.941 | B8: 0-18270 | C8: Monto: 2300 → 2400 | D8: Monto: 2300; Banco: | E8: Monto: 2400; Banco:
A9: 45987.941 | B9: 0-18270 | C9: Banco: → BANCOMER | D9: Monto: 2400; Banco: | E9: Monto: 2400; Banco: BANCOMER
A10: 45988.941 | B10: 0-18281 | C10: Banco: → SANTANDER | D10: Monto: 1200; Banco: | E10: Monto: 1200; Banco: SANTANDER
A11: 45988.941 | B11: 0-18283 | C11: Banco: → BANCOMER | D11: Monto: 850; Banco: | E11: Monto: 850; Banco: BANCOMER
A12: 45988.941 | B12: 0-18034 | C12: Banco: → BANCOMER | D12: Monto: 1200; Banco: | E12: Monto: 1200; Banco: BANCOMER
A13: 45988.941 | B13: 0-18196 | C13: Banco: → BANAMEX | D13: Monto: 750; Banco: | E13: Monto: 750; Banco: BANAMEX
... A41: 45994.941 | B41: 0-18801 | C41: Monto: 950 → 1450; Banco: SANTANDER → | D41: Monto: 950; Banco: SANTANDER | E41: Monto: 1450; Banco:
A42: 45995.503 | B42: 0-17899 | C42: ACTUALIZACIÓN | D42: Cambios en: Banco | E42: Banco: (vacío) | F42: Banco: BANAMEX
A43: 45995.503 | B43: 0-18652 | C43: ACTUALIZACIÓN | D43: Cambios en: Banco | E43: Banco: (vacío) | F43: Banco: BANORTE
A44: 45995.503 | B44: 0-18800 | C44: ACTUALIZACIÓN | D44: Cambios en: Banco | E44: Banco: (vacío) | F44: Banco: BANAMEX
A45: 45995.503 | B45: 0-18497 | C45: ACTUALIZACIÓN | D45: Cambios en: Banco | E45: Banco: (vacío) | F45: Banco: Mercado Pago- Amarillo
A46: 45995.503 | B46: 0-18498 | C46: ACTUALIZACIÓN | D46: Cambios en: Banco | E46: Banco: (vacío) | F46: Banco: BANBAJIO
A47: 45995.503 | B47: 0-17899 | C47: ACTUALIZACIÓN | D47: Cambios en: Banco | E47: Banco: (vacío) | F47: Banco: BANAMEX
A48: 45995.503 | B48: 0-18652 | C48: ACTUALIZACIÓN | D48: Cambios en: Banco | E48: Banco: (vacío) | F48: Banco: BANORTE
A49: 45995.503 | B49: 0-18800 | C49: ACTUALIZACIÓN | D49: Cambios en: Banco | E49: Banco: (vacío) | F49: Banco: BANAMEX
